chem_ant/__init__.py
chem_ant/create_vina_config.py
chem_ant/prepare_experiment.py
chem_ant/run_experiment.py
chem_ant/select_ligands.py
chem_ant/similarity_ant.py
chem_ant/similarity_mcts.py
chem_ant/smiles.csv
chem_ant-0.1.2.data/data/smiles.csv
chem_ant-0.1.2.dist-info/LICENSE
chem_ant-0.1.2.dist-info/METADATA
chem_ant-0.1.2.dist-info/WHEEL
chem_ant-0.1.2.dist-info/entry_points.txt
chem_ant-0.1.2.dist-info/top_level.txt
chem_ant-0.1.2.dist-info/RECORD
